pyshader/__init__.py
pyshader/_coreutils.py
pyshader/_dis.py
pyshader/_generator_base.py
pyshader/_generator_bc.py
pyshader/_module.py
pyshader/_spirv_constants.py
pyshader/_types.py
pyshader/dev.py
pyshader/opcodes.py
pyshader/py.py
pyshader/stdlib.py
pyshader/wasl.py
pyshader-0.7.0.dist-info/LICENSE
pyshader-0.7.0.dist-info/METADATA
pyshader-0.7.0.dist-info/WHEEL
pyshader-0.7.0.dist-info/top_level.txt
pyshader-0.7.0.dist-info/zip-safe
pyshader-0.7.0.dist-info/RECORD
