Metadata-Version: 2.1
Name: pyshader
Version: 0.7.0
Summary: Write modern GPU shaders in Python!
Home-page: https://github.com/pygfx/pyshader
Author: Almar Klein
Author-email: almar.klein@gmail.com
License: UNKNOWN
Platform: UNKNOWN
Classifier: Development Status :: 3 - Alpha
Classifier: Intended Audience :: Developers
Classifier: License :: OSI Approved :: BSD License
Classifier: Programming Language :: Python :: 3
Classifier: Topic :: Software Development :: Libraries :: Python Modules
Classifier: Topic :: Scientific/Engineering :: Visualization
Requires-Python: >=3.6.0
